grumblr/__init__.py
grumblr/__main__.py
grumblr-0.0.5.dist-info/DESCRIPTION.rst
grumblr-0.0.5.dist-info/METADATA
grumblr-0.0.5.dist-info/RECORD
grumblr-0.0.5.dist-info/WHEEL
grumblr-0.0.5.dist-info/metadata.json
grumblr-0.0.5.dist-info/pbr.json
grumblr-0.0.5.dist-info/top_level.txt
