Metadata-Version: 2.0
Name: grumblr
Version: 0.0.5
Summary: Maintenance utility for tumblr blogs.
Home-page: https://github.com/mahmoud/grumblr
Author: Mahmoud Hashemi
Author-email: mahmoudrhashemi@gmail.com
License: BSD
Platform: any
Classifier: Topic :: Software Development :: Libraries
Classifier: Programming Language :: Python :: 2.7
Requires-Dist: ashes (==17.0.0)
Requires-Dist: boltons (==17.1.0)
Requires-Dist: gevent (==1.2.1)
Requires-Dist: progressbar (==2.3)
Requires-Dist: PyTumblr (==0.0.6)
Requires-Dist: PyYAML (==3.11)
